[
  {
    "name": "__cf_bm",
    "value": "Ifh31kd3oJNQSdglzFG2_Ex09TIg59Hsv.A.b5v7ZXU-1763989906.1254041-1.0.1.1-IkdN.PIrZYSwyrkg2OrOiLBlWPZXj3zxAvYvE13lsU5eREzzSvVx3CLrKAP5_SKT.Xm7xl7OUIM06_cuL.ARUwLU0fMLHch7dV7ypZ7vpPolTXhGybqyVLtlPx09.I_N",
    "domain": ".x.com",
    "path": "/"
  },
  {
    "name": "__cuid",
    "value": "c7b6c3eabc004c969c1dfd3c751f8b57",
    "domain": ".x.com",
    "path": "/"
  },
  {
    "name": "auth_token",
    "value": "ad6a52753c739d2d8b6b386ed528578dea183c4b",
    "domain": ".x.com",
    "path": "/"
  },
  {
    "name": "ct0",
    "value": "0ad046ed698bf87ed7716cbe5aa30c088853619fa73e9fb7c9ea0cbe081803cc6fdbeba6709fc51c8a5bb9c9ee16b438f6dc0771e7fec9a05f082f645e462b828f4ccbbf52fbc4b9bd5600407fd00db2",
    "domain": ".x.com",
    "path": "/"
  },
  {
    "name": "external_referer",
    "value": "padhuUp37zjgzgv1mFWxJ12Ozwit7owX|0|8e8t2xd8A2w%3D",
    "domain": ".x.com",
    "path": "/"
  },
  {
    "name": "g_state",
    "value": "{\"i_l\":0,\"i_ll\":1763524918776,\"i_b\":\"yMqR4ALw1hSUDP52s95jsRC9X+QQJ08G0JtMeFeocmc\"}",
    "domain": "x.com",
    "path": "/"
  },
  {
    "name": "guest_id",
    "value": "v1%3A176352484722261391",
    "domain": ".x.com",
    "path": "/"
  },
  {
    "name": "guest_id_ads",
    "value": "v1%3A176352484722261391",
    "domain": ".x.com",
    "path": "/"
  },
  {
    "name": "guest_id_marketing",
    "value": "v1%3A176352484722261391",
    "domain": ".x.com",
    "path": "/"
  },
  {
    "name": "kdt",
    "value": "lEnnPsy9ZvCFJcF6ZF0c0ggXvNWamDMx7BIuPxnb",
    "domain": ".x.com",
    "path": "/"
  },
  {
    "name": "lang",
    "value": "en",
    "domain": "x.com",
    "path": "/"
  },
  {
    "name": "personalization_id",
    "value": "v1_03Lsc9zhKS1aw98UP+dH3A==",
    "domain": ".x.com",
    "path": "/"
  },
  {
    "name": "twid",
    "value": "u%3D1990993932021608449",
    "domain": ".x.com",
    "path": "/"
  }
]
